Solverz/__init__.py
Solverz/_version.py
Solverz/code_printer/__init__.py
Solverz/code_printer/make_module.py
Solverz/code_printer/matlab/__init__.py
Solverz/code_printer/matlab/matlab_printer.py
Solverz/code_printer/python/__init__.py
Solverz/code_printer/python/utilities.py
Solverz/code_printer/python/inline/__init__.py
Solverz/code_printer/python/inline/inline_printer.py
Solverz/code_printer/python/inline/tests/__init__.py
Solverz/code_printer/python/inline/tests/test_inline_printer.py
Solverz/code_printer/python/module/__init__.py
Solverz/code_printer/python/module/module_generator.py
Solverz/code_printer/python/module/module_printer.py
Solverz/code_printer/python/module/test/__init__.py
Solverz/code_printer/python/module/test/test_module_generator.py
Solverz/code_printer/python/module/test/test_module_printer.py
Solverz/code_printer/python/tests/__init__.py
Solverz/code_printer/python/tests/test_utilities.py
Solverz/equation/__init__.py
Solverz/equation/eqn.py
Solverz/equation/equations.py
Solverz/equation/hvp.py
Solverz/equation/jac.py
Solverz/equation/param.py
Solverz/equation/trigger.py
Solverz/equation/test/__init__.py
Solverz/equation/test/test_DAE.py
Solverz/equation/test/test_Param.py
Solverz/equation/test/test_eqn.py
Solverz/equation/test/test_hvp.py
Solverz/equation/test/test_jac.py
Solverz/model/__init__.py
Solverz/model/basic.py
Solverz/num_api/Array.py
Solverz/num_api/__init__.py
Solverz/num_api/custom_function.py
Solverz/num_api/module_parser.py
Solverz/num_api/num_eqn.py
Solverz/num_api/numjac.py
Solverz/num_api/test/__init__.py
Solverz/num_api/test/test_Array.py
Solverz/num_api/test/test_custom_func.py
Solverz/num_api/test/test_numjac.py
Solverz/num_api/test/test_udm.py
Solverz/solvers/__init__.py
Solverz/solvers/fdesolver.py
Solverz/solvers/laesolver.py
Solverz/solvers/option.py
Solverz/solvers/parser.py
Solverz/solvers/solution.py
Solverz/solvers/stats.py
Solverz/solvers/daesolver/__init__.py
Solverz/solvers/daesolver/beuler.py
solverz-0.6.1.dist-info/licenses/LICENSE
solverz-0.6.1.dist-info/METADATA
solverz-0.6.1.dist-info/WHEEL
solverz-0.6.1.dist-info/top_level.txt
solverz-0.6.1.dist-info/RECORD
