Metadata-Version: 2.4
Name: Solverz
Version: 0.6.1
Summary: A simulation modelling language
Author-email: Ruizhi Yu <rz.yu@foxmail.com>
Project-URL: Homepage, https://github.com/smallbunnies/Solverz
Project-URL: Issues, https://github.com/smallbunnies/Solverz/issues
Classifier: Programming Language :: Python :: 3.10
Classifier: Programming Language :: Python :: 3.11
Classifier: Programming Language :: Python :: 3.12
Classifier: License :: OSI Approved :: MIT License
Classifier: Operating System :: OS Independent
Requires-Python: >=3.10
License-File: LICENSE
Requires-Dist: sympy<=1.13.3,>=1.13.0
Requires-Dist: numba>=0.58.1
Requires-Dist: numpy>=2.0.0
Requires-Dist: scipy>=1.14.0
Requires-Dist: dill>=0.3.7
Requires-Dist: pandas>=1.4.2
Requires-Dist: openpyxl>=3.0.10
Requires-Dist: matplotlib>3.9.0
Requires-Dist: tqdm>=4.64.1
Requires-Dist: pytest>=7.2.2
Requires-Dist: pytest-datadir>=1.5.0
Requires-Dist: networkx>=3.1
Dynamic: license-file
